reata/__futures__.py
reata/__init__.py
reata/client.py
reata/schema.py
reata-1.1.6.dist-info/LICENSE
reata-1.1.6.dist-info/METADATA
reata-1.1.6.dist-info/WHEEL
reata-1.1.6.dist-info/top_level.txt
reata-1.1.6.dist-info/RECORD
