Metadata-Version: 2.1
Name: reata
Version: 1.1.6
Summary: A simple MySQL DBAPI wrapper for simplifying data processing pipelines.
License: GNU GENERAL PUBLIC LICENSE
Requires-Python: >=3.10.4
License-File: LICENSE
Requires-Dist: numpy (>=1.22.3)
Requires-Dist: pandas (>=1.4.2)
Requires-Dist: pdxtra (>=1.0.0)
Requires-Dist: mysql-connector-python (>=8.0.31)
